mbp/__init__.py
mbp/core.py
mbp/info.py
mbp/llm.py
mbp/sync.py
mbp-1.7.4.dist-info/licenses/LICENSE
mbp-1.7.4.dist-info/METADATA
mbp-1.7.4.dist-info/WHEEL
mbp-1.7.4.dist-info/top_level.txt
mbp-1.7.4.dist-info/RECORD
