Metadata-Version: 2.4
Name: mbp
Version: 1.7.4
Summary: Make Python even more beautiful :) This package includes implementations that you wish were in the standard library.
Author: Dongqi Su
License: MIT
Project-URL: Homepage, https://github.com/sudongqi/MoreBeautifulPython
Classifier: Programming Language :: Python :: 3
Classifier: License :: OSI Approved :: MIT License
Classifier: Operating System :: OS Independent
Requires-Python: >=3.11.0
License-File: LICENSE
Requires-Dist: wcwidth>=0.2.13
Requires-Dist: pyyaml>=6.0.2
Requires-Dist: termcolor>=3.2.0
Dynamic: license-file
